resolve_march_native/__init__.py
resolve_march_native/__main__.py
resolve_march_native/environment.py
resolve_march_native/messenger.py
resolve_march_native/recommended.py
resolve_march_native/sort.py
resolve_march_native/version.py
resolve_march_native/_clang/__init__.py
resolve_march_native/_clang/engine.py
resolve_march_native/_clang/parser.py
resolve_march_native/_gcc/__init__.py
resolve_march_native/_gcc/engine.py
resolve_march_native/_gcc/parser.py
resolve_march_native/_gcc/runner.py
resolve_march_native/_gcc/target_help_parser.py
resolve_march_native-6.0.1.dist-info/METADATA
resolve_march_native-6.0.1.dist-info/WHEEL
resolve_march_native-6.0.1.dist-info/entry_points.txt
resolve_march_native-6.0.1.dist-info/top_level.txt
resolve_march_native-6.0.1.dist-info/RECORD
