Metadata-Version: 2.1
Name: resolve-march-native
Version: 6.0.1
Summary: Tool to determine what GCC flags -march=native would resolve into
Home-page: https://github.com/hartwork/resolve-march-native
Author: Sebastian Pipping
Author-email: sebastian@pipping.org
License: GPLv2+
Classifier: Development Status :: 4 - Beta
Classifier: Environment :: Console
Classifier: Intended Audience :: End Users/Desktop
Classifier: Intended Audience :: System Administrators
Classifier: License :: OSI Approved :: GNU General Public License v2 or later (GPLv2+)
Classifier: Natural Language :: English
Classifier: Operating System :: POSIX :: Linux
Classifier: Programming Language :: Python
Classifier: Programming Language :: Python :: 3
Classifier: Programming Language :: Python :: 3.9
Classifier: Programming Language :: Python :: 3.10
Classifier: Programming Language :: Python :: 3.11
Classifier: Programming Language :: Python :: 3.12
Classifier: Programming Language :: Python :: 3.13
Classifier: Programming Language :: Python :: 3 :: Only
Classifier: Topic :: Software Development :: Compilers
Classifier: Topic :: Utilities
Requires-Python: >=3.9
